.gitignore
CHANGES.txt
CONTRIBUTORS.txt
MANIFEST.in
README.rst
setup.py
docs/LICENSE.GPL
docs/LICENSE.txt
plomino/__init__.py
plomino.tablib.egg-info/PKG-INFO
plomino.tablib.egg-info/SOURCES.txt
plomino.tablib.egg-info/dependency_links.txt
plomino.tablib.egg-info/entry_points.txt
plomino.tablib.egg-info/namespace_packages.txt
plomino.tablib.egg-info/not-zip-safe
plomino.tablib.egg-info/requires.txt
plomino.tablib.egg-info/top_level.txt
plomino/tablib/__init__.py