Metadata-Version: 1.1
Name: plomino.tablib
Version: 1.1
Summary: Make Tablib by Kenneth Reitz available to PlominoUtils.
Home-page: http://github.com/jean/plomino.tablib
Author: Jean Jordaan
Author-email: jean.jordaan@gmail.com
License: gpl
Platform: UNKNOWN
Classifier: Programming Language :: Python
